CONTRIBUTING.rst
LICENSE
MANIFEST.in
README.rst
cweather.py
setup.py
cweather.egg-info/PKG-INFO
cweather.egg-info/SOURCES.txt
cweather.egg-info/dependency_links.txt
cweather.egg-info/entry_points.txt
cweather.egg-info/requires.txt
cweather.egg-info/top_level.txt