Metadata-Version: 1.2
Name: cweather
Version: 0.0.1
Summary: Weather for your command line, with pretty colors
Home-page: https://github.com/jackrosenthal/cweather
Author: Jack Rosenthal
Author-email: jack@rosenth.al
License: MIT
Keywords: weather commandline
Platform: UNKNOWN
Classifier: Development Status :: 4 - Beta
Classifier: Intended Audience :: End Users/Desktop
Classifier: Operating System :: OS Independent
Classifier: License :: OSI Approved :: MIT License
Classifier: Programming Language :: Python :: 3
Classifier: Programming Language :: Python :: 3.4
Classifier: Programming Language :: Python :: 3.5
Classifier: Programming Language :: Python :: 3.6
Requires-Python: >=3.4, <4
